odoo/addons/maintenance_equipment_hierarchy/README.rst
odoo/addons/maintenance_equipment_hierarchy/__init__.py
odoo/addons/maintenance_equipment_hierarchy/__manifest__.py
odoo/addons/maintenance_equipment_hierarchy/data/demo_maintenance_equipment_hierarchy.xml
odoo/addons/maintenance_equipment_hierarchy/i18n/es.po
odoo/addons/maintenance_equipment_hierarchy/i18n/fr.po
odoo/addons/maintenance_equipment_hierarchy/i18n/it.po
odoo/addons/maintenance_equipment_hierarchy/i18n/maintenance_equipment_hierarchy.pot
odoo/addons/maintenance_equipment_hierarchy/i18n/pt.po
odoo/addons/maintenance_equipment_hierarchy/models/__init__.py
odoo/addons/maintenance_equipment_hierarchy/models/maintenance_equipment.py
odoo/addons/maintenance_equipment_hierarchy/readme/CONTRIBUTORS.rst
odoo/addons/maintenance_equipment_hierarchy/readme/DESCRIPTION.rst
odoo/addons/maintenance_equipment_hierarchy/static/description/icon.png
odoo/addons/maintenance_equipment_hierarchy/static/description/index.html
odoo/addons/maintenance_equipment_hierarchy/tests/__init__.py
odoo/addons/maintenance_equipment_hierarchy/tests/test_maintenance_equipment_hierarchy.py
odoo/addons/maintenance_equipment_hierarchy/views/maintenance_equipment_views.xml
odoo14_addon_maintenance_equipment_hierarchy-14.0.1.0.2.dist-info/METADATA
odoo14_addon_maintenance_equipment_hierarchy-14.0.1.0.2.dist-info/WHEEL
odoo14_addon_maintenance_equipment_hierarchy-14.0.1.0.2.dist-info/top_level.txt
odoo14_addon_maintenance_equipment_hierarchy-14.0.1.0.2.dist-info/RECORD
